README.md
setup.py
libpp/__init__.py
libpp.egg-info/PKG-INFO
libpp.egg-info/SOURCES.txt
libpp.egg-info/dependency_links.txt
libpp.egg-info/not-zip-safe
libpp.egg-info/requires.txt
libpp.egg-info/top_level.txt
libpp/misc/__init__.py
libpp/misc/feat_gen.py
libpp/misc/utils.py
libpp/pytorch/__init__.py
libpp/pytorch/base.py