Metadata-Version: 1.2
Name: libpp
Version: 0.0.8
Summary: peng's python library
Home-page: https://github.com/chmod740/libpp
Author: hupeng,zhangpeng
Author-email: hupeng@webprague.com
License: Apache License 2.0
Platform: UNKNOWN
Requires-Python: >=3.5
